{
    "frmdateb7": {
        "required": true,
        "type": "string",
        "formatting": "date",
        "regex": "(^(0[1-9]|1[0-2])[-/](0[1-9]|[12][0-9]|3[01])[-/](\\d{4})$)|(^(\\d{4})[-/](0[1-9]|1[0-2])[-/](0[1-9]|[12][0-9]|3[01])$)"
    },
    "langb7": {
        "required": true,
        "type": "integer",
        "allowed": [
            1,
            2
        ]
    },
    "modeb7": {
        "required": true,
        "type": "integer",
        "allowed": [
            0,
            1,
            2
        ]
    },
    "rmreasb7": {
        "nullable": true,
        "type": "integer",
        "compatibility": [
            {
                "index": 0,
                "if": {
                    "modeb7": {
                        "allowed": [
                            2
                        ]
                    }
                },
                "then": {
                    "rmreasb7": {
                        "nullable": false
                    }
                }
            },
            {
                "index": 1,
                "if": {
                    "modeb7": {
                        "allowed": [
                            0,
                            1
                        ]
                    }
                },
                "then": {
                    "rmreasb7": {
                        "nullable": true,
                        "filled": false
                    }
                }
            }
        ],
        "allowed": [
            1,
            2,
            3,
            4,
            5
        ]
    },
    "rmmodeb7": {
        "nullable": true,
        "type": "integer",
        "compatibility": [
            {
                "index": 0,
                "if": {
                    "modeb7": {
                        "allowed": [
                            2
                        ]
                    }
                },
                "then": {
                    "rmmodeb7": {
                        "nullable": false
                    }
                }
            },
            {
                "index": 1,
                "if": {
                    "modeb7": {
                        "allowed": [
                            0,
                            1
                        ]
                    }
                },
                "then": {
                    "rmmodeb7": {
                        "nullable": true,
                        "filled": false
                    }
                }
            }
        ],
        "allowed": [
            1,
            2
        ]
    },
    "b7not": {
        "nullable": true,
        "type": "integer",
        "compatibility": [
            {
                "index": 0,
                "if": {
                    "modeb7": {
                        "allowed": [
                            0
                        ]
                    }
                },
                "then": {
                    "b7not": {
                        "nullable": false
                    }
                }
            },
            {
                "index": 1,
                "if": {
                    "modeb7": {
                        "allowed": [
                            1,
                            2
                        ]
                    }
                },
                "then": {
                    "b7not": {
                        "nullable": true,
                        "filled": false
                    }
                }
            }
        ],
        "allowed": [
            95,
            96,
            97,
            98
        ]
    },
    "bills": {
        "required": true,
        "type": "integer",
        "allowed": [
            0,
            1,
            2,
            3,
            8,
            9
        ]
    },
    "taxes": {
        "required": true,
        "type": "integer",
        "allowed": [
            0,
            1,
            2,
            3,
            8,
            9
        ]
    },
    "shopping": {
        "required": true,
        "type": "integer",
        "allowed": [
            0,
            1,
            2,
            3,
            8,
            9
        ]
    },
    "games": {
        "required": true,
        "type": "integer",
        "allowed": [
            0,
            1,
            2,
            3,
            8,
            9
        ]
    },
    "stove": {
        "required": true,
        "type": "integer",
        "allowed": [
            0,
            1,
            2,
            3,
            8,
            9
        ]
    },
    "mealprep": {
        "required": true,
        "type": "integer",
        "allowed": [
            0,
            1,
            2,
            3,
            8,
            9
        ],
        "compatibility": [
            {
                "index": 0,
                "if": {
                    "stove": {
                        "allowed": [
                            0
                        ]
                    }
                },
                "then": {
                    "mealprep": {
                        "forbidden": [
                            3
                        ],
                        "nullable": true
                    }
                }
            },
            {
                "index": 1,
                "if": {
                    "stove": {
                        "allowed": [
                            3
                        ]
                    }
                },
                "then": {
                    "mealprep": {
                        "forbidden": [
                            0
                        ],
                        "nullable": true
                    }
                }
            }
        ]
    },
    "events": {
        "required": true,
        "type": "integer",
        "allowed": [
            0,
            1,
            2,
            3,
            8,
            9
        ]
    },
    "payattn": {
        "required": true,
        "type": "integer",
        "allowed": [
            0,
            1,
            2,
            3,
            8,
            9
        ]
    },
    "remdates": {
        "required": true,
        "type": "integer",
        "allowed": [
            0,
            1,
            2,
            3,
            8,
            9
        ]
    },
    "travel": {
        "required": true,
        "type": "integer",
        "allowed": [
            0,
            1,
            2,
            3,
            8,
            9
        ]
    },
    "initialsb7": {
        "nullable": true,
        "type": "string"
    }
}