{
    "frmdateb7": {
        "nullable": true
    },
    "langb7": {
        "nullable": true
    },
    "modeb7": {
        "required": true,
        "type": "integer",
        "allowed": [
            0
        ]
    },
    "rmreasb7": {
        "nullable": true,
        "filled": false
    },
    "rmmodeb7": {
        "nullable": true,
        "filled": false
    },
    "b7not": {
        "type": "integer",
        "allowed": [
            95,
            96,
            97,
            98
        ],
        "required": true
    },
    "bills": {
        "nullable": true,
        "filled": false
    },
    "taxes": {
        "nullable": true,
        "filled": false
    },
    "shopping": {
        "nullable": true,
        "filled": false
    },
    "games": {
        "nullable": true,
        "filled": false
    },
    "stove": {
        "nullable": true,
        "filled": false
    },
    "mealprep": {
        "nullable": true,
        "filled": false
    },
    "events": {
        "nullable": true,
        "filled": false
    },
    "payattn": {
        "nullable": true,
        "filled": false
    },
    "remdates": {
        "nullable": true,
        "filled": false
    },
    "travel": {
        "nullable": true,
        "filled": false
    },
    "initialsb7": {
        "nullable": true
    }
}